[{"__symbolic":"module","version":4,"metadata":{"BLEScanOptions":{"__symbolic":"interface"},"BLE":{"__symbolic":"class","extends":{"__symbolic":"reference","module":"@ionic-native/core","name":"IonicNativePlugin","line":185,"character":25},"decorators":[{"__symbolic":"call","expression":{"__symbolic":"reference","module":"@angular/core","name":"Injectable","line":184,"character":1}}],"members":{"scan":[{"__symbolic":"method"}],"startScan":[{"__symbolic":"method"}],"startScanWithOptions":[{"__symbolic":"method"}],"stopScan":[{"__symbolic":"method"}],"connect":[{"__symbolic":"method"}],"autoConnect":[{"__symbolic":"method"}],"requestMtu":[{"__symbolic":"method"}],"refreshDeviceCache":[{"__symbolic":"method"}],"disconnect":[{"__symbolic":"method"}],"read":[{"__symbolic":"method"}],"write":[{"__symbolic":"method"}],"writeWithoutResponse":[{"__symbolic":"method"}],"startNotification":[{"__symbolic":"method"}],"stopNotification":[{"__symbolic":"method"}],"isConnected":[{"__symbolic":"method"}],"isEnabled":[{"__symbolic":"method"}],"startStateNotifications":[{"__symbolic":"method"}],"stopStateNotifications":[{"__symbolic":"method"}],"showBluetoothSettings":[{"__symbolic":"method"}],"enable":[{"__symbolic":"method"}],"readRSSI":[{"__symbolic":"method"}],"connectedPeripheralsWithServices":[{"__symbolic":"method"}],"peripheralsWithIdentifiers":[{"__symbolic":"method"}],"bondedDevices":[{"__symbolic":"method"}]}}}}]
