[{"__symbolic":"module","version":4,"metadata":{"CloudSettings":{"__symbolic":"class","extends":{"__symbolic":"reference","module":"@ionic-native/core","name":"IonicNativePlugin","line":41,"character":35},"decorators":[{"__symbolic":"call","expression":{"__symbolic":"reference","module":"@angular/core","name":"Injectable","line":40,"character":1}}],"members":{"exists":[{"__symbolic":"method"}],"save":[{"__symbolic":"method"}],"load":[{"__symbolic":"method"}],"onRestore":[{"__symbolic":"method"}],"enableDebug":[{"__symbolic":"method"}]}}}}]
