[{"__symbolic":"module","version":4,"metadata":{"BioCatch":{"__symbolic":"class","extends":{"__symbolic":"reference","module":"@ionic-native/core","name":"IonicNativePlugin","line":32,"character":30},"decorators":[{"__symbolic":"call","expression":{"__symbolic":"reference","module":"@angular/core","name":"Injectable","line":31,"character":1}}],"members":{"start":[{"__symbolic":"method"}],"pause":[{"__symbolic":"method"}],"resume":[{"__symbolic":"method"}],"stop":[{"__symbolic":"method"}],"resetSession":[{"__symbolic":"method"}],"changeContext":[{"__symbolic":"method"}],"updateCustomerSessionID":[{"__symbolic":"method"}]}}}}]
